PyGASP-0.2.1.dist-info/DESCRIPTION.rst
PyGASP-0.2.1.dist-info/METADATA
PyGASP-0.2.1.dist-info/RECORD
PyGASP-0.2.1.dist-info/WHEEL
PyGASP-0.2.1.dist-info/metadata.json
PyGASP-0.2.1.dist-info/top_level.txt
pygasp/__init__.py
pygasp/dct.py
pygasp/dctCuda.py
pygasp/dwt.py
pygasp/dwtCuda.py
pygasp/dwtFilters.py
pygasp/dwtGUI.py
pygasp/fftCuda.py
pygasp/fftFilters.py
pygasp/fftIterative.py
pygasp/fftRecursive.py
test/__init__.py
test/test_dct.py
test/test_dctCuda.py
test/test_dwt.py
test/test_dwtCuda.py
test/test_fft.py
test/test_fftCuda.py
