Metadata-Version: 2.0
Name: PyGASP
Version: 0.2.1
Summary: A GPU-accelerated signal processing library.
Home-page: http://packages.python.org/PyGASP
Author: Erin Carrier, Nathan Bowman
Author-email: bowmanat@mail.gvsu.edu
License: MIT
Keywords: signal processing,science,PyCUDA,DWT,FFT,DCT
Platform: UNKNOWN
Classifier: Development Status :: 3 - Alpha
Classifier: Topic :: Utilities
Classifier: License :: OSI Approved :: MIT License
Classifier: Natural Language :: English
Classifier: Topic :: Scientific/Engineering
